starling/__init__.py
starling/starling.py
starling/utility.py
biostarling-0.1.4.dist-info/LICENSE.txt
biostarling-0.1.4.dist-info/METADATA
biostarling-0.1.4.dist-info/WHEEL
biostarling-0.1.4.dist-info/RECORD
