Metadata-Version: 2.1
Name: biostarling
Version: 0.1.4
Summary: Segmentation error aware clustering single-cell spatial expression data
Home-page: https://github.com/camlab-bioml/starling
License: See License.txt
Keywords: imaging cytometry classifier single-cell
Author: Jett (Yuju) Lee
Author-email: yulee@lunenfeld.ca
Requires-Python: >=3.9,<3.13
Classifier: Intended Audience :: Science/Research
Classifier: License :: Other/Proprietary License
Classifier: Programming Language :: Python :: 3
Classifier: Programming Language :: Python :: 3.9
Classifier: Programming Language :: Python :: 3.10
Classifier: Programming Language :: Python :: 3.11
Classifier: Programming Language :: Python :: 3.12
Requires-Dist: flowsom (>=0.1.1,<0.2.0)
Requires-Dist: numpy (>=1.26,<2.0)
Requires-Dist: pandas (>=0.23.0)
Requires-Dist: phenograph (>=1.5.7,<2.0.0)
Requires-Dist: pytorch-lightning (>=2.3.3,<3.0.0)
Requires-Dist: scanpy (>=1.10.2,<2.0.0)
Requires-Dist: torch (>=2.4.0,<3.0.0)
Project-URL: Repository, https://github.com/camlab-bioml/starling
